{
  "model_size": "tiny",
  "n_params": 1967232,
  "lr": 1e-05,
  "train_losses": [
    {
      "step": 0,
      "loss": 8.31777,
      "lr": 6.666666666666667e-08
    },
    {
      "step": 15,
      "loss": 8.31766,
      "lr": 1.0666666666666667e-06
    },
    {
      "step": 30,
      "loss": 8.31737,
      "lr": 2.0666666666666666e-06
    },
    {
      "step": 45,
      "loss": 8.31684,
      "lr": 3.066666666666667e-06
    },
    {
      "step": 60,
      "loss": 8.31611,
      "lr": 4.066666666666667e-06
    },
    {
      "step": 75,
      "loss": 8.31502,
      "lr": 5.066666666666667e-06
    },
    {
      "step": 90,
      "loss": 8.31358,
      "lr": 6.066666666666667e-06
    },
    {
      "step": 105,
      "loss": 8.31194,
      "lr": 7.066666666666668e-06
    },
    {
      "step": 120,
      "loss": 8.31018,
      "lr": 8.066666666666667e-06
    },
    {
      "step": 135,
      "loss": 8.3075,
      "lr": 9.066666666666667e-06
    },
    {
      "step": 150,
      "loss": 8.30432,
      "lr": 1e-05
    },
    {
      "step": 165,
      "loss": 8.30093,
      "lr": 9.999384872466112e-06
    },
    {
      "step": 180,
      "loss": 8.29633,
      "lr": 9.997539658034168e-06
    },
    {
      "step": 195,
      "loss": 8.29287,
      "lr": 9.994464861167373e-06
    },
    {
      "step": 210,
      "loss": 8.28786,
      "lr": 9.990161322484486e-06
    },
    {
      "step": 225,
      "loss": 8.28407,
      "lr": 9.984630218530016e-06
    },
    {
      "step": 240,
      "loss": 8.27892,
      "lr": 9.977873061452553e-06
    },
    {
      "step": 255,
      "loss": 8.27493,
      "lr": 9.969891698591373e-06
    },
    {
      "step": 270,
      "loss": 8.26889,
      "lr": 9.960688311971389e-06
    },
    {
      "step": 285,
      "loss": 8.26307,
      "lr": 9.95026541770661e-06
    },
    {
      "step": 300,
      "loss": 8.25909,
      "lr": 9.938625865312252e-06
    },
    {
      "step": 315,
      "loss": 8.25135,
      "lr": 9.92577283692572e-06
    },
    {
      "step": 330,
      "loss": 8.24268,
      "lr": 9.911709846436643e-06
    },
    {
      "step": 345,
      "loss": 8.2388,
      "lr": 9.896440738526197e-06
    },
    {
      "step": 360,
      "loss": 8.23362,
      "lr": 9.879969687616028e-06
    },
    {
      "step": 375,
      "loss": 8.22463,
      "lr": 9.862301196726988e-06
    },
    {
      "step": 390,
      "loss": 8.21882,
      "lr": 9.84344009624807e-06
    },
    {
      "step": 405,
      "loss": 8.21296,
      "lr": 9.823391542615818e-06
    },
    {
      "step": 420,
      "loss": 8.20243,
      "lr": 9.80216101690461e-06
    },
    {
      "step": 435,
      "loss": 8.1945,
      "lr": 9.779754323328192e-06
    },
    {
      "step": 450,
      "loss": 8.18905,
      "lr": 9.756177587652857e-06
    },
    {
      "step": 465,
      "loss": 8.18696,
      "lr": 9.731437255522726e-06
    },
    {
      "step": 480,
      "loss": 8.17567,
      "lr": 9.705540090697574e-06
    },
    {
      "step": 495,
      "loss": 8.16685,
      "lr": 9.678493173203682e-06
    },
    {
      "step": 510,
      "loss": 8.16129,
      "lr": 9.650303897398232e-06
    },
    {
      "step": 525,
      "loss": 8.15343,
      "lr": 9.620979969947759e-06
    },
    {
      "step": 540,
      "loss": 8.14106,
      "lr": 9.590529407721232e-06
    },
    {
      "step": 555,
      "loss": 8.13377,
      "lr": 9.558960535598316e-06
    },
    {
      "step": 570,
      "loss": 8.12451,
      "lr": 9.526281984193437e-06
    },
    {
      "step": 585,
      "loss": 8.1192,
      "lr": 9.492502687496253e-06
    },
    {
      "step": 600,
      "loss": 8.10441,
      "lr": 9.4576318804292e-06
    },
    {
      "step": 615,
      "loss": 8.10269,
      "lr": 9.421679096322748e-06
    },
    {
      "step": 630,
      "loss": 8.10121,
      "lr": 9.384654164309083e-06
    },
    {
      "step": 645,
      "loss": 8.08525,
      "lr": 9.346567206634927e-06
    },
    {
      "step": 660,
      "loss": 8.08039,
      "lr": 9.30742863589421e-06
    },
    {
      "step": 675,
      "loss": 8.07489,
      "lr": 9.267249152181379e-06
    },
    {
      "step": 690,
      "loss": 8.05904,
      "lr": 9.226039740166091e-06
    },
    {
      "step": 705,
      "loss": 8.05414,
      "lr": 9.183811666090118e-06
    },
    {
      "step": 720,
      "loss": 8.05156,
      "lr": 9.140576474687265e-06
    },
    {
      "step": 735,
      "loss": 8.03096,
      "lr": 9.096345986027162e-06
    },
    {
      "step": 750,
      "loss": 8.02501,
      "lr": 9.051132292283772e-06
    },
    {
      "step": 765,
      "loss": 8.02386,
      "lr": 9.004947754429508e-06
    },
    {
      "step": 780,
      "loss": 8.01428,
      "lr": 8.957804998855866e-06
    },
    {
      "step": 795,
      "loss": 8.006,
      "lr": 8.909716913921507e-06
    },
    {
      "step": 810,
      "loss": 7.99795,
      "lr": 8.860696646428693e-06
    },
    {
      "step": 825,
      "loss": 7.99081,
      "lr": 8.810757598029094e-06
    },
    {
      "step": 840,
      "loss": 7.97884,
      "lr": 8.759913421559902e-06
    },
    {
      "step": 855,
      "loss": 7.96864,
      "lr": 8.708178017311287e-06
    },
    {
      "step": 870,
      "loss": 7.96298,
      "lr": 8.655565529226199e-06
    },
    {
      "step": 885,
      "loss": 7.94615,
      "lr": 8.602090341033547e-06
    },
    {
      "step": 900,
      "loss": 7.94488,
      "lr": 8.547767072315835e-06
    },
    {
      "step": 915,
      "loss": 7.94329,
      "lr": 8.492610574512317e-06
    },
    {
      "step": 930,
      "loss": 7.92778,
      "lr": 8.43663592685876e-06
    },
    {
      "step": 945,
      "loss": 7.92756,
      "lr": 8.379858432264926e-06
    },
    {
      "step": 960,
      "loss": 7.91181,
      "lr": 8.322293613130917e-06
    },
    {
      "step": 975,
      "loss": 7.90821,
      "lr": 8.263957207103506e-06
    },
    {
      "step": 990,
      "loss": 7.89988,
      "lr": 8.204865162773613e-06
    },
    {
      "step": 1005,
      "loss": 7.89133,
      "lr": 8.14503363531613e-06
    },
    {
      "step": 1020,
      "loss": 7.88438,
      "lr": 8.084478982073247e-06
    },
    {
      "step": 1035,
      "loss": 7.87723,
      "lr": 8.023217758082527e-06
    },
    {
      "step": 1050,
      "loss": 7.86632,
      "lr": 7.961266711550922e-06
    },
    {
      "step": 1065,
      "loss": 7.8645,
      "lr": 7.898642779275972e-06
    },
    {
      "step": 1080,
      "loss": 7.85121,
      "lr": 7.83536308201547e-06
    },
    {
      "step": 1095,
      "loss": 7.85594,
      "lr": 7.771444919806798e-06
    },
    {
      "step": 1110,
      "loss": 7.83985,
      "lr": 7.706905767237288e-06
    },
    {
      "step": 1125,
      "loss": 7.83773,
      "lr": 7.641763268666832e-06
    },
    {
      "step": 1140,
      "loss": 7.82907,
      "lr": 7.576035233404095e-06
    },
    {
      "step": 1155,
      "loss": 7.82889,
      "lr": 7.50973963083763e-06
    },
    {
      "step": 1170,
      "loss": 7.81191,
      "lr": 7.442894585523219e-06
    },
    {
      "step": 1185,
      "loss": 7.80588,
      "lr": 7.3755183722288066e-06
    },
    {
      "step": 1200,
      "loss": 7.7831,
      "lr": 7.307629410938363e-06
    },
    {
      "step": 1215,
      "loss": 7.7876,
      "lr": 7.239246261816035e-06
    },
    {
      "step": 1230,
      "loss": 7.79765,
      "lr": 7.1703876201319935e-06
    },
    {
      "step": 1245,
      "loss": 7.78094,
      "lr": 7.101072311151325e-06
    },
    {
      "step": 1260,
      "loss": 7.77843,
      "lr": 7.031319284987395e-06
    },
    {
      "step": 1275,
      "loss": 7.78601,
      "lr": 6.961147611421077e-06
    },
    {
      "step": 1290,
      "loss": 7.75738,
      "lr": 6.8905764746872645e-06
    },
    {
      "step": 1305,
      "loss": 7.74221,
      "lr": 6.819625168230093e-06
    },
    {
      "step": 1320,
      "loss": 7.75641,
      "lr": 6.7483130894283e-06
    },
    {
      "step": 1335,
      "loss": 7.7336,
      "lr": 6.676659734292189e-06
    },
    {
      "step": 1350,
      "loss": 7.74953,
      "lr": 6.604684692133597e-06
    },
    {
      "step": 1365,
      "loss": 7.72776,
      "lr": 6.532407640210383e-06
    },
    {
      "step": 1380,
      "loss": 7.73485,
      "lr": 6.459848338346862e-06
    },
    {
      "step": 1395,
      "loss": 7.7244,
      "lr": 6.387026623531662e-06
    },
    {
      "step": 1410,
      "loss": 7.72127,
      "lr": 6.313962404494496e-06
    },
    {
      "step": 1425,
      "loss": 7.71453,
      "lr": 6.240675656263304e-06
    },
    {
      "step": 1440,
      "loss": 7.68092,
      "lr": 6.16718641470329e-06
    },
    {
      "step": 1455,
      "loss": 7.69057,
      "lr": 6.093514771039311e-06
    },
    {
      "step": 1470,
      "loss": 7.70203,
      "lr": 6.019680866363138e-06
    },
    {
      "step": 1485,
      "loss": 7.70307,
      "lr": 5.945704886127083e-06
    },
    {
      "step": 1500,
      "loss": 7.68622,
      "lr": 5.871607054625496e-06
    },
    {
      "step": 1515,
      "loss": 7.69786,
      "lr": 5.797407629465647e-06
    },
    {
      "step": 1530,
      "loss": 7.67063,
      "lr": 5.723126896029501e-06
    },
    {
      "step": 1545,
      "loss": 7.66217,
      "lr": 5.648785161927886e-06
    },
    {
      "step": 1560,
      "loss": 7.65693,
      "lr": 5.574402751448614e-06
    },
    {
      "step": 1575,
      "loss": 7.67027,
      "lr": 5.5e-06
    },
    {
      "step": 1590,
      "loss": 7.65953,
      "lr": 5.4255972485513875e-06
    },
    {
      "step": 1605,
      "loss": 7.64464,
      "lr": 5.351214838072113e-06
    },
    {
      "step": 1620,
      "loss": 7.65251,
      "lr": 5.276873103970499e-06
    },
    {
      "step": 1635,
      "loss": 7.63288,
      "lr": 5.2025923705343525e-06
    },
    {
      "step": 1650,
      "loss": 7.62859,
      "lr": 5.1283929453745055e-06
    },
    {
      "step": 1665,
      "loss": 7.63325,
      "lr": 5.054295113872919e-06
    },
    {
      "step": 1680,
      "loss": 7.61931,
      "lr": 4.980319133636863e-06
    },
    {
      "step": 1695,
      "loss": 7.65065,
      "lr": 4.90648522896069e-06
    },
    {
      "step": 1710,
      "loss": 7.60427,
      "lr": 4.832813585296712e-06
    },
    {
      "step": 1725,
      "loss": 7.61285,
      "lr": 4.759324343736697e-06
    },
    {
      "step": 1740,
      "loss": 7.63058,
      "lr": 4.686037595505507e-06
    },
    {
      "step": 1755,
      "loss": 7.60224,
      "lr": 4.6129733764683395e-06
    },
    {
      "step": 1770,
      "loss": 7.61416,
      "lr": 4.5401516616531395e-06
    },
    {
      "step": 1785,
      "loss": 7.62433,
      "lr": 4.467592359789619e-06
    },
    {
      "step": 1800,
      "loss": 7.59346,
      "lr": 4.395315307866404e-06
    },
    {
      "step": 1815,
      "loss": 7.59112,
      "lr": 4.323340265707811e-06
    },
    {
      "step": 1830,
      "loss": 7.58359,
      "lr": 4.251686910571701e-06
    },
    {
      "step": 1845,
      "loss": 7.56821,
      "lr": 4.1803748317699094e-06
    },
    {
      "step": 1860,
      "loss": 7.54961,
      "lr": 4.109423525312737e-06
    },
    {
      "step": 1875,
      "loss": 7.57554,
      "lr": 4.038852388578925e-06
    },
    {
      "step": 1890,
      "loss": 7.58281,
      "lr": 3.968680715012607e-06
    },
    {
      "step": 1905,
      "loss": 7.55661,
      "lr": 3.898927688848675e-06
    },
    {
      "step": 1920,
      "loss": 7.54733,
      "lr": 3.829612379868006e-06
    },
    {
      "step": 1935,
      "loss": 7.57683,
      "lr": 3.7607537381839664e-06
    },
    {
      "step": 1950,
      "loss": 7.5466,
      "lr": 3.6923705890616385e-06
    },
    {
      "step": 1965,
      "loss": 7.55046,
      "lr": 3.6244816277711944e-06
    },
    {
      "step": 1980,
      "loss": 7.56579,
      "lr": 3.5571054144767827e-06
    },
    {
      "step": 1995,
      "loss": 7.56094,
      "lr": 3.490260369162371e-06
    },
    {
      "step": 2010,
      "loss": 7.53006,
      "lr": 3.423964766595905e-06
    },
    {
      "step": 2025,
      "loss": 7.55089,
      "lr": 3.3582367313331692e-06
    },
    {
      "step": 2040,
      "loss": 7.54536,
      "lr": 3.293094232762715e-06
    },
    {
      "step": 2055,
      "loss": 7.52575,
      "lr": 3.228555080193205e-06
    },
    {
      "step": 2070,
      "loss": 7.53385,
      "lr": 3.1646369179845332e-06
    },
    {
      "step": 2085,
      "loss": 7.53287,
      "lr": 3.1013572207240293e-06
    },
    {
      "step": 2100,
      "loss": 7.54611,
      "lr": 3.03873328844908e-06
    },
    {
      "step": 2115,
      "loss": 7.54934,
      "lr": 2.9767822419174734e-06
    },
    {
      "step": 2130,
      "loss": 7.49805,
      "lr": 2.915521017926754e-06
    },
    {
      "step": 2145,
      "loss": 7.51515,
      "lr": 2.8549663646838717e-06
    },
    {
      "step": 2160,
      "loss": 7.487,
      "lr": 2.795134837226387e-06
    },
    {
      "step": 2175,
      "loss": 7.50438,
      "lr": 2.736042792896495e-06
    },
    {
      "step": 2190,
      "loss": 7.5019,
      "lr": 2.6777063868690836e-06
    },
    {
      "step": 2205,
      "loss": 7.49673,
      "lr": 2.6201415677350753e-06
    },
    {
      "step": 2220,
      "loss": 7.49192,
      "lr": 2.5633640731412414e-06
    },
    {
      "step": 2235,
      "loss": 7.50543,
      "lr": 2.5073894254876826e-06
    },
    {
      "step": 2250,
      "loss": 7.48778,
      "lr": 2.452232927684166e-06
    },
    {
      "step": 2265,
      "loss": 7.52413,
      "lr": 2.397909658966454e-06
    },
    {
      "step": 2280,
      "loss": 7.49242,
      "lr": 2.3444344707738017e-06
    },
    {
      "step": 2295,
      "loss": 7.4903,
      "lr": 2.2918219826887137e-06
    },
    {
      "step": 2310,
      "loss": 7.48792,
      "lr": 2.2400865784401e-06
    },
    {
      "step": 2325,
      "loss": 7.49401,
      "lr": 2.1892424019709082e-06
    },
    {
      "step": 2340,
      "loss": 7.49935,
      "lr": 2.139303353571309e-06
    },
    {
      "step": 2355,
      "loss": 7.48714,
      "lr": 2.0902830860784954e-06
    },
    {
      "step": 2370,
      "loss": 7.49512,
      "lr": 2.042195001144136e-06
    },
    {
      "step": 2385,
      "loss": 7.47759,
      "lr": 1.9950522455704945e-06
    },
    {
      "step": 2400,
      "loss": 7.48822,
      "lr": 1.94886770771623e-06
    },
    {
      "step": 2415,
      "loss": 7.49496,
      "lr": 1.903654013972839e-06
    },
    {
      "step": 2430,
      "loss": 7.48576,
      "lr": 1.8594235253127373e-06
    },
    {
      "step": 2445,
      "loss": 7.48113,
      "lr": 1.8161883339098845e-06
    },
    {
      "step": 2460,
      "loss": 7.47261,
      "lr": 1.77396025983391e-06
    },
    {
      "step": 2475,
      "loss": 7.47811,
      "lr": 1.7327508478186216e-06
    },
    {
      "step": 2490,
      "loss": 7.47762,
      "lr": 1.6925713641057902e-06
    },
    {
      "step": 2505,
      "loss": 7.45356,
      "lr": 1.6534327933650741e-06
    },
    {
      "step": 2520,
      "loss": 7.47666,
      "lr": 1.615345835690917e-06
    },
    {
      "step": 2535,
      "loss": 7.47085,
      "lr": 1.5783209036772519e-06
    },
    {
      "step": 2550,
      "loss": 7.46044,
      "lr": 1.5423681195707997e-06
    },
    {
      "step": 2565,
      "loss": 7.46489,
      "lr": 1.507497312503747e-06
    },
    {
      "step": 2580,
      "loss": 7.4736,
      "lr": 1.4737180158065645e-06
    },
    {
      "step": 2595,
      "loss": 7.46422,
      "lr": 1.441039464401685e-06
    },
    {
      "step": 2610,
      "loss": 7.45723,
      "lr": 1.409470592278769e-06
    },
    {
      "step": 2625,
      "loss": 7.47211,
      "lr": 1.3790200300522415e-06
    },
    {
      "step": 2640,
      "loss": 7.44949,
      "lr": 1.3496961026017689e-06
    },
    {
      "step": 2655,
      "loss": 7.47264,
      "lr": 1.321506826796319e-06
    },
    {
      "step": 2670,
      "loss": 7.45986,
      "lr": 1.2944599093024268e-06
    },
    {
      "step": 2685,
      "loss": 7.43984,
      "lr": 1.2685627444772749e-06
    },
    {
      "step": 2700,
      "loss": 7.45876,
      "lr": 1.2438224123471444e-06
    },
    {
      "step": 2715,
      "loss": 7.47541,
      "lr": 1.2202456766718092e-06
    },
    {
      "step": 2730,
      "loss": 7.42854,
      "lr": 1.1978389830953908e-06
    },
    {
      "step": 2745,
      "loss": 7.44981,
      "lr": 1.1766084573841836e-06
    },
    {
      "step": 2760,
      "loss": 7.46587,
      "lr": 1.1565599037519317e-06
    },
    {
      "step": 2775,
      "loss": 7.46665,
      "lr": 1.1376988032730135e-06
    },
    {
      "step": 2790,
      "loss": 7.45434,
      "lr": 1.1200303123839744e-06
    },
    {
      "step": 2805,
      "loss": 7.44393,
      "lr": 1.1035592614738034e-06
    },
    {
      "step": 2820,
      "loss": 7.43741,
      "lr": 1.088290153563358e-06
    },
    {
      "step": 2835,
      "loss": 7.43612,
      "lr": 1.0742271630742795e-06
    },
    {
      "step": 2850,
      "loss": 7.45637,
      "lr": 1.0613741346877498e-06
    },
    {
      "step": 2865,
      "loss": 7.45674,
      "lr": 1.049734582293392e-06
    },
    {
      "step": 2880,
      "loss": 7.45393,
      "lr": 1.0393116880286117e-06
    },
    {
      "step": 2895,
      "loss": 7.44273,
      "lr": 1.0301083014086284e-06
    },
    {
      "step": 2910,
      "loss": 7.50861,
      "lr": 1.0221269385474488e-06
    },
    {
      "step": 2925,
      "loss": 7.44074,
      "lr": 1.0153697814699858e-06
    },
    {
      "step": 2940,
      "loss": 7.45497,
      "lr": 1.0098386775155147e-06
    },
    {
      "step": 2955,
      "loss": 7.44395,
      "lr": 1.0055351388326289e-06
    },
    {
      "step": 2970,
      "loss": 7.4504,
      "lr": 1.0024603419658329e-06
    },
    {
      "step": 2985,
      "loss": 7.46653,
      "lr": 1.0006151275338897e-06
    },
    {
      "step": 2999,
      "loss": 7.44387,
      "lr": 1.0000027339621613e-06
    }
  ],
  "val_loss": 7.438902,
  "wall_clock_s": 1098.18,
  "tokens_per_sec": 44758,
  "gpu_mem_gb": 0.32
}